minipot/__init__.py
minipot/booster.py
minipot/utils.py
minitonupot-0.0.1.dist-info/licenses/LICENSE
minitonupot-0.0.1.dist-info/METADATA
minitonupot-0.0.1.dist-info/WHEEL
minitonupot-0.0.1.dist-info/top_level.txt
minitonupot-0.0.1.dist-info/RECORD
