Metadata-Version: 2.4
Name: minitonupot
Version: 0.0.1
Summary: Mini potenciador de Minitonu que mejora capacidades clave en un 15-20%.
Author-email: Luis Fernando Montaño <gachaprimosxd128@gmail.com>
Project-URL: Homepage, https://pypi.org/project/minipot
Requires-Python: >=3.7
License-File: LICENSE
Requires-Dist: minitonu>=0.0.1.1b1
Dynamic: license-file
